nf2/__init__.py
nf2/extrapolate.py
nf2/extrapolate_series.py
nf2/convert/__init__.py
nf2/convert/convert_series.py
nf2/convert/muram_to_vtk.py
nf2/convert/nf2_to_fits.py
nf2/convert/nf2_to_hdf5.py
nf2/convert/nf2_to_npy.py
nf2/convert/nf2_to_vtk.py
nf2/convert/nf2_to_vtk_spherical.py
nf2/convert/potential_vtk.py
nf2/data/__init__.py
nf2/data/analytical_field.py
nf2/data/combine_sst_hmi.py
nf2/data/convert_coordinates.py
nf2/data/convert_muram_slices.py
nf2/data/dataset.py
nf2/data/download.py
nf2/data/download_euv.py
nf2/data/download_full_disk.py
nf2/data/download_range.py
nf2/data/download_sharp.py
nf2/data/download_synoptic.py
nf2/data/get_coordinate_bounds.py
nf2/data/loader.py
nf2/data/noaa_to_sharp.py
nf2/data/util.py
nf2/data/sst/__init__.py
nf2/data/sst/mask.py
nf2/data/sst/prep.py
nf2/evaluation/__init__.py
nf2/evaluation/compute_metrics.py
nf2/evaluation/current_series.py
nf2/evaluation/energy.py
nf2/evaluation/metric.py
nf2/evaluation/output.py
nf2/evaluation/output_metrics.py
nf2/evaluation/parameters.py
nf2/evaluation/plot_carrington_map.py
nf2/evaluation/plot_euv_comparison.py
nf2/evaluation/plot_kso_comparison.py
nf2/evaluation/unpack.py
nf2/evaluation/vtk.py
nf2/evaluation/analytical/__init__.py
nf2/evaluation/analytical/corrugation.py
nf2/evaluation/analytical/metrics.py
nf2/evaluation/mfr/__init__.py
nf2/evaluation/muram/__init__.py
nf2/evaluation/muram/compare_boundary.py
nf2/evaluation/muram/compare_currents.py
nf2/evaluation/muram/corrugation.py
nf2/evaluation/muram/cube_height.py
nf2/evaluation/muram/height_ff.py
nf2/evaluation/muram/height_metrics.py
nf2/evaluation/muram/metrics.py
nf2/evaluation/muram/potential_metrics.py
nf2/evaluation/muram/slices.py
nf2/evaluation/sharp/__init__.py
nf2/evaluation/sharp/convert_series.py
nf2/evaluation/sharp/ensemble.py
nf2/evaluation/sharp/flares.py
nf2/evaluation/sharp/plot_current_series.py
nf2/evaluation/sharp/plot_euv_lightcurve.py
nf2/evaluation/sharp/plot_integrated_energy.py
nf2-0.3.dist-info/LICENSE
nf2-0.3.dist-info/METADATA
nf2-0.3.dist-info/WHEEL
nf2-0.3.dist-info/entry_points.txt
nf2-0.3.dist-info/top_level.txt
nf2-0.3.dist-info/RECORD
