Metadata-Version: 2.1
Name: nf2
Version: 0.3
Summary: Neural Network Force Free magnetic field extrapolation
Home-page: https://github.com/RobertJaro/NF2
Author: Robert Jarolim
Author-email: 
License: GNU GENERAL PUBLIC LICENSE
License-File: LICENSE
Requires-Dist: torch >=1.8
Requires-Dist: sunpy[all] >=3.0
Requires-Dist: scikit-image
Requires-Dist: scikit-learn
Requires-Dist: tqdm
Requires-Dist: numpy
Requires-Dist: matplotlib
Requires-Dist: astropy
Requires-Dist: drms
Requires-Dist: wandb >=0.13
Requires-Dist: lightning ==1.9.3
Requires-Dist: pytorch-lightning ==1.9.3
Requires-Dist: pfsspy
